Metadata-Version: 2.1
Name: kurumii-nokeyboard
Version: 1.3.2
Summary: A handy litle tool
Home-page: UNKNOWN
Author: Kurumii
License: UNKNOWN
Platform: UNKNOWN
